{
    "keep": {
        "days": true,
        "amount": 1
    },
    "auditLog": "R:\\projects\\lira-backend\\winston\\success\\.c6978dcd0db56af07e3f848907efc1f38046d64d-audit.json",
    "files": [
        {
            "date": 1761030001674,
            "name": "R:\\projects\\lira-backend\\winston\\success\\21-10-2025-13-success.log",
            "hash": "088bd36706f93dce88d03e0a230efafc604bf238f538eef30873ab0fa27e47f5"
        },
        {
            "date": 1761036150639,
            "name": "R:\\projects\\lira-backend\\winston\\success\\21-10-2025-14-success.log",
            "hash": "07f6ea1112ddcb11fdf8336e01e5714cefe82ced766830fd584e89e539d32706"
        },
        {
            "date": 1761037280998,
            "name": "R:\\projects\\lira-backend\\winston\\success\\21-10-2025-15-success.log",
            "hash": "04f418ced5e5e0a3af87e271c4c4bf9b730c69a7dff0f7b409ab21205d530325"
        },
        {
            "date": 1761040988953,
            "name": "R:\\projects\\lira-backend\\winston\\success\\21-10-2025-16-success.log",
            "hash": "27b1700d0518b3ac9ce4a40f50b0332098f75c5d7d201390cbf264bd3474e91e"
        },
        {
            "date": 1761044429941,
            "name": "R:\\projects\\lira-backend\\winston\\success\\21-10-2025-17-success.log",
            "hash": "dcbc3e4f13d33a3cf26f2fb8d5607a8e5a4be850f0f212f1696e1e90748da0d2"
        },
        {
            "date": 1761048226681,
            "name": "R:\\projects\\lira-backend\\winston\\success\\21-10-2025-18-success.log",
            "hash": "2f6f7ae7e0e5280492512f416dc8e69879aad3c51a6f320fae3f4a936a878496"
        },
        {
            "date": 1761051688904,
            "name": "R:\\projects\\lira-backend\\winston\\success\\21-10-2025-19-success.log",
            "hash": "b40402aa7740096f0b1e7705f61e99820a9bd71dde96c884719d55fc06de879f"
        },
        {
            "date": 1761103391389,
            "name": "R:\\projects\\lira-backend\\winston\\success\\22-10-2025-09-success.log",
            "hash": "e1ffdc19b70f53af97b214bd7bd3e4954fc2fd1a49b18d50d0c9558505c49fda"
        },
        {
            "date": 1761105912021,
            "name": "R:\\projects\\lira-backend\\winston\\success\\22-10-2025-10-success.log",
            "hash": "9f06024b4d7bc7e57083de5592944a919139dbdcff2033c5db0709be13adf589"
        },
        {
            "date": 1761109310341,
            "name": "R:\\projects\\lira-backend\\winston\\success\\22-10-2025-11-success.log",
            "hash": "e1c1d99a336c589331ffbdc5cc601eb98d13c3f3ded22b1c5d85c234c0b7bec1"
        },
        {
            "date": 1761113716317,
            "name": "R:\\projects\\lira-backend\\winston\\success\\22-10-2025-12-success.log",
            "hash": "c6681e91f7deb42e28a9f19ba6e6bc610ce4ea6481229b402899f6e5d92d8755"
        }
    ],
    "hashType": "sha256"
}