{
    "keep": {
        "days": true,
        "amount": 1
    },
    "auditLog": "R:\\projects\\lira-backend\\winston\\error\\.9b740fde61954cb3233620f0ce221323516f9792-audit.json",
    "files": [
        {
            "date": 1760327127198,
            "name": "R:\\projects\\lira-backend\\winston\\error\\13-10-2025-09-error.log",
            "hash": "6b1bc9cadca53d3ddac51d7e476c089acd73f1790ee524294fc76347e302abb5"
        },
        {
            "date": 1760328160852,
            "name": "R:\\projects\\lira-backend\\winston\\error\\13-10-2025-10-error.log",
            "hash": "064620eae2bc3a59609ca446cb7bf33519979113335bcbc302651e9c47b8f0e7"
        },
        {
            "date": 1760333225563,
            "name": "R:\\projects\\lira-backend\\winston\\error\\13-10-2025-11-error.log",
            "hash": "ea1619afff2ffe1fa3164f65510d602e9f5938a065dd1ee8616355572e1630c4"
        },
        {
            "date": 1760336794371,
            "name": "R:\\projects\\lira-backend\\winston\\error\\13-10-2025-12-error.log",
            "hash": "356ac56987ef1879d390faabe48d55e2c7994bed3fb68eb2caaec67e68b7f900"
        },
        {
            "date": 1760338887688,
            "name": "R:\\projects\\lira-backend\\winston\\error\\13-10-2025-13-error.log",
            "hash": "950f627a4fbb61a7703aca9fb536396eaf9077763356fed9de903651cfffb094"
        },
        {
            "date": 1760347030374,
            "name": "R:\\projects\\lira-backend\\winston\\error\\13-10-2025-15-error.log",
            "hash": "b7d6a71e95db1686ac890aae276ef2a8d27c0aab5a06ee0742c697b3ebba41e4"
        },
        {
            "date": 1760413276290,
            "name": "R:\\projects\\lira-backend\\winston\\error\\14-10-2025-09-error.log",
            "hash": "aaed8faf9d311aeebc07fb3eeb5a59f1cdb7f8d20d2fd86b9ffdd8b87f252f44"
        }
    ],
    "hashType": "sha256"
}